sflkitlib/__init__.py
sflkitlib/lib.py
sflkitlib/events/__init__.py
sflkitlib/events/codec.py
sflkitlib/events/event.py
sflkitlib-0.2.2.dist-info/LICENSE
sflkitlib-0.2.2.dist-info/METADATA
sflkitlib-0.2.2.dist-info/WHEEL
sflkitlib-0.2.2.dist-info/top_level.txt
sflkitlib-0.2.2.dist-info/RECORD
