Metadata-Version: 2.1
Name: sflkitlib
Version: 0.2.2
Summary: Lib for SFLKit: : A Workbench for Statistical Fault Localization
Home-page: https://github.com/smythi93/sflkit-lib
Author: Marius Smytzek
Author-email: marius.smytzek@cispa.de
License: MIT License
Project-URL: Bug Tracker, https://github.com/smythi93/sflkit-lib/issues
Platform: UNKNOWN
Classifier: Intended Audience :: Science/Research
Classifier: Programming Language :: Python :: 3.6
Classifier: License :: OSI Approved :: Apache Software License
Classifier: License :: OSI Approved :: MIT License
Classifier: Topic :: Scientific/Engineering
Classifier: Topic :: Software Development :: Testing
Requires-Python: >=3.6
License-File: LICENSE
Provides-Extra: dev
Provides-Extra: test
